OgreInterface/__init__.py
OgreInterface/example.py
OgreInterface/lattice_match.py
OgreInterface/miller.py
OgreInterface/utils.py
OgreInterface/data/__init__.py
OgreInterface/data/ionic_radii.py
OgreInterface/data/ionic_radii_data.csv
OgreInterface/data/universal_lennard_jones_parameters.py
OgreInterface/data/universal_lennard_jones_parameters_old.csv
OgreInterface/generate/__init__.py
OgreInterface/generate/base_surface_generator.py
OgreInterface/generate/interface_generator.py
OgreInterface/generate/molecular_surface_generator.py
OgreInterface/generate/surface_generator.py
OgreInterface/interfaces/__init__.py
OgreInterface/interfaces/base_interface.py
OgreInterface/interfaces/interface.py
OgreInterface/interfaces/molecular_interface.py
OgreInterface/plotting_tools/__init__.py
OgreInterface/plotting_tools/colors.py
OgreInterface/plotting_tools/match_plotter.py
OgreInterface/plotting_tools/plotting_utils.py
OgreInterface/plotting_tools/surface_charge_plot.py
OgreInterface/randomizer/interface_randomizer.py
OgreInterface/randomizer/interface_switch_and_rattle.py
OgreInterface/surface_matching/__init__.py
OgreInterface/surface_matching/base_surface_energy.py
OgreInterface/surface_matching/base_surface_matcher.py
OgreInterface/surface_matching/chgnet_surface_matcher/__init__.py
OgreInterface/surface_matching/chgnet_surface_matcher/chgnet_surface_energy.py
OgreInterface/surface_matching/chgnet_surface_matcher/chgnet_surface_matcher.py
OgreInterface/surface_matching/ionic_surface_matcher/__init__.py
OgreInterface/surface_matching/ionic_surface_matcher/input_generator.py
OgreInterface/surface_matching/ionic_surface_matcher/ionic_shifted_force_potential.py
OgreInterface/surface_matching/ionic_surface_matcher/ionic_surface_energy.py
OgreInterface/surface_matching/ionic_surface_matcher/ionic_surface_matcher.py
OgreInterface/surface_matching/ionic_surface_matcher/scatter_add.py
OgreInterface/surface_matching/ionic_surface_matcher/utils.py
OgreInterface-1.2.17.dist-info/LICENSE.txt
OgreInterface-1.2.17.dist-info/METADATA
OgreInterface-1.2.17.dist-info/WHEEL
OgreInterface-1.2.17.dist-info/top_level.txt
OgreInterface-1.2.17.dist-info/RECORD
