Metadata-Version: 2.1
Name: OgreInterface
Version: 1.2.17
Summary: A Python library used to generate and optimize epitaxial inorganic interface structures.
Author-email: Derek Dardzinski <dardzinski.derek@gmail.com>
Project-URL: source, https://github.com/DerekDardzinski/OgreInterface
Requires-Python: >=3.9
License-File: LICENSE.txt
Requires-Dist: pymatgen
Requires-Dist: matplotlib
Requires-Dist: numpy
Requires-Dist: tqdm
Requires-Dist: ase
Requires-Dist: scikit-opt
Requires-Dist: cmcrameri
Requires-Dist: seaborn
Requires-Dist: matscipy
Requires-Dist: scipy
Requires-Dist: pandas <=2.0.0
Requires-Dist: XlsxWriter
